SentiAnalyzer/Main_tensor_model.py
SentiAnalyzer/SentiToolKit.keras
SentiAnalyzer/__init__.py
SentiAnalyzer/tokenizer.pkl
tests/__init__.py
tests/tests_model.py
SentiToolKit-0.1.51.dist-info/LICENSE
SentiToolKit-0.1.51.dist-info/METADATA
SentiToolKit-0.1.51.dist-info/WHEEL
SentiToolKit-0.1.51.dist-info/entry_points.txt
SentiToolKit-0.1.51.dist-info/top_level.txt
SentiToolKit-0.1.51.dist-info/RECORD
