Metadata-Version: 2.1
Name: SentiToolKit
Version: 0.1.51
Summary: A sentiment analysis toolkit using a trained TensorFlow model
Home-page: https://github.com/Niall1985/SentiToolKit
Author: Niall Dcunha
Author-email: dcunhaniall@gmail.com
Classifier: Programming Language :: Python :: 3
Classifier: License :: OSI Approved :: GNU Affero General Public License v3
Classifier: Operating System :: OS Independent
Requires-Python: >=3.6
License-File: LICENSE
Requires-Dist: tensorflow >=2.0
Requires-Dist: scikit-learn
